Metadata-Version: 1.0
Name: despik-package
Version: 0.6
Summary: Some work with yfinance for self education
Home-page: UNKNOWN
Author: UNKNOWN
Author-email: artomonik@gmail.com
License: UNKNOWN
Platform: UNKNOWN
